requirements.txt
setup.py
setuppy_generator/__init__.py
setuppy_generator/__main__.py
setuppy_generator.egg-info/PKG-INFO
setuppy_generator.egg-info/SOURCES.txt
setuppy_generator.egg-info/dependency_links.txt
setuppy_generator.egg-info/requires.txt
setuppy_generator.egg-info/top_level.txt