Metadata-Version: 2.1
Name: setuppy-generator
Version: 2020.7.1
Summary: setup.py generator
Home-page: https://github.com/andrewp-as-is/setuppy-generator.py
License: Unlicense
Keywords: setup.py setup generator
Platform: UNKNOWN
Classifier: License :: Public Domain
Classifier: Operating System :: OS Independent
Classifier: Programming Language :: Python :: 3
